next_gen_ui_llama_stack_embedded/__init__.py
next_gen_ui_llama_stack_embedded/llama_stack_inference_embedded.py
next_gen_ui_llama_stack_embedded-0.3.0.dist-info/METADATA
next_gen_ui_llama_stack_embedded-0.3.0.dist-info/WHEEL
next_gen_ui_llama_stack_embedded-0.3.0.dist-info/namespace_packages.txt
next_gen_ui_llama_stack_embedded-0.3.0.dist-info/top_level.txt
next_gen_ui_llama_stack_embedded-0.3.0.dist-info/RECORD
