Metadata-Version: 2.1
Name: next_gen_ui_llama_stack_embedded
Version: 0.3.0
Summary: Embedded Llama-Stack server inference for Next Gen UI Agent
Home-page: https://github.com/RedHat-UX/next-gen-ui-agent
License: Apache-2.0
Classifier: Programming Language :: Python :: 3
Classifier: Programming Language :: Python :: 3.12
Classifier: Programming Language :: Python :: 3.13
Classifier: License :: OSI Approved :: Apache Software License
Requires-Python: <3.14,>=3.12
Requires-Dist: aiosqlite
Requires-Dist: blobfile
Requires-Dist: fastapi
Requires-Dist: fire
Requires-Dist: litellm
Requires-Dist: llama-stack-client>=0.2.15
Requires-Dist: llama-stack==0.2.20
Requires-Dist: next-gen-ui-agent==0.3.0
Requires-Dist: next-gen-ui-llama-stack==0.3.0
Requires-Dist: ollama
Requires-Dist: opentelemetry-exporter-otlp
Requires-Dist: opentelemetry-instrumentation
Requires-Dist: opentelemetry-sdk
Requires-Dist: overrides
Requires-Dist: requests
Requires-Dist: uvicorn
